{
  "$schema": "https://json-schema.org/draft/2020-12/schema",
  "type": "array",
  "items": {
    "type": "object",
    "required": ["team", "solved", "penalty", "problems"],
    "properties": {
      "team": {
        "type": "string"
      },
      "solved": {
        "type": "integer"
      },
      "penalty": {
        "type": "integer"
      },
      "problems": {
        "type": "object",
        "additionalProperties": {
          "type": "object",
          "required": ["solved", "attempts"],
          "properties": {
            "solved": {
              "type": "boolean"
            },
            "attempts": {
              "type": "integer"
            },
            "time": {
              "type": "integer"
            }
          }
        }
      }
    }
  }
}